[
  {
    "id": "PUB-01",
    "query": "We are a small enterprise manufacturing 33 Grade Ordinary Portland Cement. Which BIS standard covers the chemical and physical requirements for our product?",
    "expected_standards": [
      "IS 269: 1989"
    ],
    "retrieved_standards": [
      "IS 269 : 1989",
      "IS 8112 : 1989",
      "IS 269:1989"
    ],
    "latency_seconds": 7.9757
  },
  {
    "id": "PUB-02",
    "query": "I need to comply with the regulations for coarse and fine aggregates derived from natural sources intended for use in structural concrete.",
    "expected_standards": [
      "IS 383: 1970"
    ],
    "retrieved_standards": [
      "IS 383 : 1970",
      "IS 383:1970",
      "IS 1195 : 2002"
    ],
    "latency_seconds": 8.9217
  },
  {
    "id": "PUB-03",
    "query": "What is the official specification for manufacturing precast concrete pipes, both with and without reinforcement, for water mains?",
    "expected_standards": [
      "IS 458: 2003"
    ],
    "retrieved_standards": [
      "IS 458 : 2003"
    ],
    "latency_seconds": 6.2099
  },
  {
    "id": "PUB-04",
    "query": "Our company is shifting to manufacturing hollow and solid lightweight concrete masonry blocks. What standard outlines the dimensions and physical requirements?",
    "expected_standards": [
      "IS 2185 (Part 2): 1983"
    ],
    "retrieved_standards": [
      "IS 2185 (Part 2)",
      "IS 2185",
      "IS 2185 (Part 2):1983"
    ],
    "latency_seconds": 7.9972
  },
  {
    "id": "PUB-05",
    "query": "Looking for the standard detailing corrugated and semi-corrugated asbestos cement sheets used for roofing and cladding.",
    "expected_standards": [
      "IS 459: 1992"
    ],
    "retrieved_standards": [
      "IS 14871 : 2000",
      "IS 459:1992",
      "IS 459 : 1992"
    ],
    "latency_seconds": 3.1073
  },
  {
    "id": "PUB-06",
    "query": "What is the Indian Standard covering the manufacture, chemical, and physical requirements for Portland slag cement?",
    "expected_standards": [
      "IS 455: 1989"
    ],
    "retrieved_standards": [
      "IS 12089:1987",
      "IS 8112 : 1989",
      "IS 455 : 1989"
    ],
    "latency_seconds": 3.2896
  },
  {
    "id": "PUB-07",
    "query": "We are setting up a plant to produce Portland pozzolana cement that is calcined clay based. What is the applicable standard?",
    "expected_standards": [
      "IS 1489 (Part 2): 1991"
    ],
    "retrieved_standards": [
      "IS 1489",
      "IS 1489(Part 2):1991",
      "IS 1489 (Part 1)"
    ],
    "latency_seconds": 3.2123
  },
  {
    "id": "PUB-08",
    "query": "Which standard applies to masonry cement used for general purposes where mortars for masonry are required, but not intended for structural concrete?",
    "expected_standards": [
      "IS 3466: 1988"
    ],
    "retrieved_standards": [
      "IS 3466 : 1988",
      "IS 8273:1984",
      "IS 2116:1980"
    ],
    "latency_seconds": 5.2865
  },
  {
    "id": "PUB-09",
    "query": "Looking for the standard that details the composition, manufacture, and testing of supersulphated cement, particularly for marine works or aggressive water conditions.",
    "expected_standards": [
      "IS 6909: 1990"
    ],
    "retrieved_standards": [
      "IS 6909 : 1990",
      "IS 6441",
      "IS 10175 (Part 1) :1993"
    ],
    "latency_seconds": 3.1449
  },
  {
    "id": "PUB-10",
    "query": "Our company manufactures White Portland cement for architectural and decorative purposes. Which standard governs its physical and chemical requirements?",
    "expected_standards": [
      "IS 8042: 1989"
    ],
    "retrieved_standards": [
      "IS 8042 : 1989",
      "IS 269: 1989",
      "IS 8043 : 1991"
    ],
    "latency_seconds": 3.1876
  }
]